ngc/__init__.py
ngc/main.py
pnu_ngc-1.0.2.data/data/man/man1/ngc.1.gz
pnu_ngc-1.0.2.dist-info/License
pnu_ngc-1.0.2.dist-info/METADATA
pnu_ngc-1.0.2.dist-info/WHEEL
pnu_ngc-1.0.2.dist-info/entry_points.txt
pnu_ngc-1.0.2.dist-info/top_level.txt
pnu_ngc-1.0.2.dist-info/RECORD
